{"num_c": 100, "num_v": 25, "vehicles": {"0": [200, 1], "1": [200, 1], "2": [200, 1], "3": [200, 1], "4": [200, 1], "5": [200, 1], "6": [200, 1], "7": [200, 1], "8": [200, 1], "9": [200, 1], "10": [200, 1], "11": [200, 1], "12": [200, 1], "13": [200, 1], "14": [200, 1], "15": [200, 1], "16": [200, 1], "17": [200, 1], "18": [200, 1], "19": [200, 1], "20": [200, 1], "21": [200, 1], "22": [200, 1], "23": [200, 1], "24": [200, 1]}, "customers": {"00": {"coords": [35, 35], "demand": 0, "service": 0, "windows": [{"day": 0, "start": 0, "end": 230}, {"day": 1, "start": 0, "end": 230}, {"day": 2, "start": 0, "end": 230}, {"day": 3, "start": 0, "end": 230}, {"day": 4, "start": 0, "end": 230}, {"day": 5, "start": 0, "end": 230}, {"day": 6, "start": 0, "end": 230}, {"day": 7, "start": 0, "end": 230}, {"day": 8, "start": 0, "end": 230}, {"day": 9, "start": 0, "end": 230}, {"day": 10, "start": 0, "end": 230}, {"day": 11, "start": 0, "end": 230}, {"day": 12, "start": 0, "end": 230}, {"day": 13, "start": 0, "end": 230}, {"day": 14, "start": 0, "end": 230}, {"day": 15, "start": 0, "end": 230}, {"day": 16, "start": 0, "end": 230}, {"day": 17, "start": 0, "end": 230}, {"day": 18, "start": 0, "end": 230}, {"day": 19, "start": 0, "end": 230}, {"day": 20, "start": 0, "end": 230}, {"day": 21, "start": 0, "end": 230}, {"day": 22, "start": 0, "end": 230}, {"day": 23, "start": 0, "end": 230}, {"day": 24, "start": 0, "end": 230}]}, "01": {"coords": [41, 49], "demand": 10, "service": 10, "windows": [{"day": 3, "start": 61, "end": 126}]}, "02": {"coords": [35, 17], "demand": 7, "service": 10, "windows": [{"day": 9, "start": 110, "end": 175}, {"day": 19, "start": 135, "end": 200}]}, "03": {"coords": [55, 45], "demand": 13, "service": 10, "windows": [{"day": 0, "start": 104, "end": 149}, {"day": 6, "start": 108, "end": 153}, {"day": 17, "start": 70, "end": 115}, {"day": 18, "start": 89, "end": 134}, {"day": 20, "start": 56, "end": 101}]}, "04": {"coords": [55, 20], "demand": 19, "service": 10, "windows": [{"day": 16, "start": 103, "end": 164}, {"day": 17, "start": 100, "end": 161}, {"day": 22, "start": 53, "end": 114}, {"day": 24, "start": 79, "end": 140}]}, "05": {"coords": [15, 30], "demand": 26, "service": 10, "windows": [{"day": 1, "start": 39, "end": 112}, {"day": 8, "start": 36, "end": 109}, {"day": 15, "start": 23, "end": 96}, {"day": 16, "start": 44, "end": 117}, {"day": 20, "start": 107, "end": 180}, {"day": 21, "start": 75, "end": 148}, {"day": 24, "start": 30, "end": 103}]}, "06": {"coords": [25, 30], "demand": 3, "service": 10, "windows": [{"day": 2, "start": 140, "end": 195}, {"day": 16, "start": 53, "end": 108}, {"day": 21, "start": 132, "end": 187}]}, "07": {"coords": [20, 50], "demand": 5, "service": 10, "windows": [{"day": 4, "start": 25, "end": 74}, {"day": 6, "start": 33, "end": 82}, {"day": 8, "start": 145, "end": 194}, {"day": 19, "start": 71, "end": 120}, {"day": 21, "start": 79, "end": 128}]}, "08": {"coords": [10, 43], "demand": 9, "service": 10, "windows": [{"day": 6, "start": 84, "end": 133}, {"day": 7, "start": 116, "end": 165}, {"day": 8, "start": 94, "end": 143}, {"day": 12, "start": 31, "end": 80}, {"day": 19, "start": 108, "end": 157}, {"day": 22, "start": 28, "end": 77}]}, "09": {"coords": [55, 60], "demand": 16, "service": 10, "windows": [{"day": 3, "start": 119, "end": 174}, {"day": 5, "start": 48, "end": 103}, {"day": 7, "start": 71, "end": 126}, {"day": 10, "start": 83, "end": 138}, {"day": 12, "start": 90, "end": 145}, {"day": 14, "start": 65, "end": 120}, {"day": 15, "start": 99, "end": 154}, {"day": 18, "start": 52, "end": 107}, {"day": 20, "start": 38, "end": 93}]}, "010": {"coords": [30, 60], "demand": 16, "service": 10, "windows": [{"day": 10, "start": 74, "end": 117}, {"day": 12, "start": 45, "end": 88}, {"day": 16, "start": 125, "end": 168}, {"day": 18, "start": 46, "end": 89}, {"day": 19, "start": 100, "end": 143}]}, "011": {"coords": [20, 65], "demand": 12, "service": 10, "windows": [{"day": 1, "start": 56, "end": 115}, {"day": 7, "start": 105, "end": 164}, {"day": 24, "start": 44, "end": 103}]}, "012": {"coords": [50, 35], "demand": 19, "service": 10, "windows": [{"day": 0, "start": 71, "end": 130}, {"day": 1, "start": 17, "end": 76}, {"day": 2, "start": 89, "end": 148}, {"day": 14, "start": 22, "end": 81}, {"day": 18, "start": 116, "end": 175}, {"day": 24, "start": 132, "end": 191}]}, "013": {"coords": [30, 25], "demand": 23, "service": 10, "windows": [{"day": 2, "start": 136, "end": 201}, {"day": 3, "start": 115, "end": 180}, {"day": 15, "start": 93, "end": 158}, {"day": 17, "start": 49, "end": 114}, {"day": 20, "start": 109, "end": 174}, {"day": 24, "start": 33, "end": 98}]}, "014": {"coords": [15, 10], "demand": 20, "service": 10, "windows": [{"day": 2, "start": 49, "end": 131}, {"day": 3, "start": 34, "end": 116}, {"day": 13, "start": 44, "end": 126}]}, "015": {"coords": [30, 5], "demand": 8, "service": 10, "windows": [{"day": 6, "start": 54, "end": 115}, {"day": 16, "start": 47, "end": 108}, {"day": 22, "start": 108, "end": 169}]}, "016": {"coords": [10, 20], "demand": 19, "service": 10, "windows": [{"day": 0, "start": 75, "end": 130}, {"day": 4, "start": 90, "end": 145}, {"day": 6, "start": 106, "end": 161}, {"day": 9, "start": 100, "end": 155}, {"day": 11, "start": 130, "end": 185}, {"day": 19, "start": 117, "end": 172}]}, "017": {"coords": [5, 30], "demand": 2, "service": 10, "windows": [{"day": 4, "start": 55, "end": 120}, {"day": 5, "start": 81, "end": 146}, {"day": 10, "start": 36, "end": 101}, {"day": 12, "start": 63, "end": 128}, {"day": 18, "start": 111, "end": 176}, {"day": 23, "start": 85, "end": 150}]}, "018": {"coords": [20, 40], "demand": 12, "service": 10, "windows": [{"day": 1, "start": 42, "end": 87}, {"day": 3, "start": 55, "end": 100}, {"day": 5, "start": 130, "end": 175}, {"day": 13, "start": 23, "end": 68}, {"day": 15, "start": 75, "end": 120}, {"day": 17, "start": 52, "end": 97}, {"day": 22, "start": 17, "end": 62}]}, "019": {"coords": [15, 60], "demand": 17, "service": 10, "windows": [{"day": 2, "start": 91, "end": 148}, {"day": 3, "start": 77, "end": 134}, {"day": 6, "start": 59, "end": 116}, {"day": 13, "start": 43, "end": 100}, {"day": 14, "start": 107, "end": 164}, {"day": 17, "start": 49, "end": 106}, {"day": 24, "start": 49, "end": 106}]}, "020": {"coords": [45, 65], "demand": 9, "service": 10, "windows": [{"day": 3, "start": 70, "end": 121}, {"day": 6, "start": 86, "end": 137}, {"day": 14, "start": 125, "end": 176}, {"day": 19, "start": 55, "end": 106}]}, "021": {"coords": [45, 20], "demand": 11, "service": 10, "windows": [{"day": 7, "start": 78, "end": 137}, {"day": 9, "start": 115, "end": 174}, {"day": 11, "start": 108, "end": 167}, {"day": 15, "start": 99, "end": 158}, {"day": 20, "start": 82, "end": 141}]}, "022": {"coords": [45, 10], "demand": 18, "service": 10, "windows": [{"day": 1, "start": 140, "end": 191}, {"day": 3, "start": 77, "end": 128}, {"day": 7, "start": 59, "end": 110}, {"day": 11, "start": 37, "end": 88}, {"day": 12, "start": 128, "end": 179}, {"day": 15, "start": 137, "end": 188}, {"day": 18, "start": 80, "end": 131}, {"day": 21, "start": 93, "end": 144}]}, "023": {"coords": [55, 5], "demand": 29, "service": 10, "windows": [{"day": 7, "start": 52, "end": 111}, {"day": 10, "start": 122, "end": 181}, {"day": 20, "start": 100, "end": 159}, {"day": 21, "start": 116, "end": 175}]}, "024": {"coords": [65, 35], "demand": 3, "service": 10, "windows": [{"day": 4, "start": 124, "end": 190}, {"day": 8, "start": 30, "end": 96}, {"day": 16, "start": 88, "end": 154}, {"day": 22, "start": 120, "end": 186}, {"day": 23, "start": 70, "end": 136}, {"day": 24, "start": 53, "end": 119}]}, "025": {"coords": [65, 20], "demand": 6, "service": 10, "windows": [{"day": 6, "start": 60, "end": 125}, {"day": 8, "start": 83, "end": 148}, {"day": 9, "start": 115, "end": 180}, {"day": 10, "start": 57, "end": 122}, {"day": 16, "start": 99, "end": 164}, {"day": 21, "start": 100, "end": 165}]}, "026": {"coords": [45, 30], "demand": 17, "service": 10, "windows": [{"day": 6, "start": 25, "end": 74}, {"day": 7, "start": 12, "end": 61}, {"day": 9, "start": 28, "end": 77}, {"day": 17, "start": 33, "end": 82}, {"day": 22, "start": 23, "end": 72}, {"day": 23, "start": 32, "end": 81}]}, "027": {"coords": [35, 40], "demand": 16, "service": 10, "windows": [{"day": 1, "start": 56, "end": 123}, {"day": 12, "start": 131, "end": 198}, {"day": 14, "start": 110, "end": 177}, {"day": 17, "start": 25, "end": 92}, {"day": 20, "start": 59, "end": 126}, {"day": 22, "start": 114, "end": 181}]}, "028": {"coords": [41, 37], "demand": 16, "service": 10, "windows": [{"day": 8, "start": 80, "end": 145}, {"day": 17, "start": 32, "end": 97}, {"day": 18, "start": 113, "end": 178}]}, "029": {"coords": [64, 42], "demand": 9, "service": 10, "windows": [{"day": 1, "start": 112, "end": 173}, {"day": 11, "start": 69, "end": 130}, {"day": 16, "start": 31, "end": 92}, {"day": 20, "start": 46, "end": 107}, {"day": 22, "start": 52, "end": 113}, {"day": 24, "start": 127, "end": 188}]}, "030": {"coords": [40, 60], "demand": 21, "service": 10, "windows": [{"day": 6, "start": 55, "end": 108}, {"day": 12, "start": 132, "end": 185}, {"day": 13, "start": 102, "end": 155}, {"day": 16, "start": 54, "end": 107}, {"day": 18, "start": 138, "end": 191}]}, "031": {"coords": [31, 52], "demand": 27, "service": 10, "windows": [{"day": 5, "start": 22, "end": 83}, {"day": 14, "start": 20, "end": 81}, {"day": 18, "start": 20, "end": 81}, {"day": 20, "start": 48, "end": 109}, {"day": 21, "start": 46, "end": 107}]}, "032": {"coords": [35, 69], "demand": 23, "service": 10, "windows": [{"day": 2, "start": 61, "end": 120}, {"day": 4, "start": 73, "end": 132}, {"day": 5, "start": 76, "end": 135}, {"day": 9, "start": 67, "end": 126}, {"day": 16, "start": 83, "end": 142}, {"day": 17, "start": 98, "end": 157}, {"day": 18, "start": 118, "end": 177}, {"day": 21, "start": 76, "end": 135}, {"day": 24, "start": 36, "end": 95}]}, "033": {"coords": [53, 52], "demand": 11, "service": 10, "windows": [{"day": 8, "start": 105, "end": 173}, {"day": 10, "start": 102, "end": 170}, {"day": 11, "start": 68, "end": 136}, {"day": 14, "start": 29, "end": 97}, {"day": 20, "start": 121, "end": 189}]}, "034": {"coords": [65, 55], "demand": 14, "service": 10, "windows": [{"day": 12, "start": 131, "end": 182}]}, "035": {"coords": [63, 65], "demand": 8, "service": 10, "windows": [{"day": 0, "start": 84, "end": 146}, {"day": 7, "start": 61, "end": 123}, {"day": 10, "start": 48, "end": 110}, {"day": 19, "start": 60, "end": 122}, {"day": 23, "start": 103, "end": 165}]}, "036": {"coords": [2, 60], "demand": 5, "service": 10, "windows": [{"day": 4, "start": 96, "end": 167}, {"day": 8, "start": 62, "end": 133}, {"day": 16, "start": 77, "end": 148}, {"day": 21, "start": 97, "end": 168}]}, "037": {"coords": [20, 20], "demand": 8, "service": 10, "windows": [{"day": 0, "start": 106, "end": 157}, {"day": 5, "start": 138, "end": 189}, {"day": 10, "start": 89, "end": 140}, {"day": 12, "start": 46, "end": 97}, {"day": 22, "start": 79, "end": 130}]}, "038": {"coords": [5, 5], "demand": 16, "service": 10, "windows": [{"day": 3, "start": 67, "end": 122}, {"day": 4, "start": 51, "end": 106}, {"day": 12, "start": 46, "end": 101}]}, "039": {"coords": [60, 12], "demand": 31, "service": 10, "windows": [{"day": 5, "start": 44, "end": 121}, {"day": 8, "start": 58, "end": 135}, {"day": 15, "start": 84, "end": 161}, {"day": 24, "start": 50, "end": 127}]}, "040": {"coords": [40, 25], "demand": 9, "service": 10, "windows": [{"day": 11, "start": 33, "end": 82}, {"day": 12, "start": 56, "end": 105}, {"day": 21, "start": 126, "end": 175}, {"day": 23, "start": 57, "end": 106}]}, "041": {"coords": [42, 7], "demand": 5, "service": 10, "windows": [{"day": 0, "start": 125, "end": 184}, {"day": 3, "start": 130, "end": 189}, {"day": 7, "start": 71, "end": 130}, {"day": 9, "start": 127, "end": 186}, {"day": 15, "start": 83, "end": 142}, {"day": 23, "start": 31, "end": 90}, {"day": 24, "start": 45, "end": 104}]}, "042": {"coords": [24, 12], "demand": 5, "service": 10, "windows": [{"day": 0, "start": 103, "end": 169}, {"day": 1, "start": 78, "end": 144}, {"day": 8, "start": 35, "end": 101}, {"day": 17, "start": 84, "end": 150}, {"day": 19, "start": 75, "end": 141}, {"day": 20, "start": 38, "end": 104}, {"day": 21, "start": 70, "end": 136}, {"day": 22, "start": 77, "end": 143}]}, "043": {"coords": [23, 3], "demand": 7, "service": 10, "windows": [{"day": 0, "start": 93, "end": 144}, {"day": 10, "start": 101, "end": 152}, {"day": 11, "start": 45, "end": 96}, {"day": 15, "start": 101, "end": 152}, {"day": 18, "start": 83, "end": 134}, {"day": 22, "start": 134, "end": 185}]}, "044": {"coords": [11, 14], "demand": 18, "service": 10, "windows": [{"day": 7, "start": 62, "end": 119}, {"day": 12, "start": 85, "end": 142}, {"day": 15, "start": 104, "end": 161}, {"day": 17, "start": 106, "end": 163}, {"day": 18, "start": 81, "end": 138}, {"day": 20, "start": 51, "end": 108}, {"day": 21, "start": 73, "end": 130}, {"day": 23, "start": 131, "end": 188}]}, "045": {"coords": [6, 38], "demand": 16, "service": 10, "windows": [{"day": 1, "start": 49, "end": 119}, {"day": 4, "start": 85, "end": 155}, {"day": 12, "start": 102, "end": 172}]}, "046": {"coords": [2, 48], "demand": 1, "service": 10, "windows": [{"day": 2, "start": 114, "end": 173}, {"day": 12, "start": 86, "end": 145}, {"day": 13, "start": 89, "end": 148}, {"day": 17, "start": 94, "end": 153}, {"day": 19, "start": 79, "end": 138}, {"day": 21, "start": 72, "end": 131}, {"day": 23, "start": 83, "end": 142}]}, "047": {"coords": [8, 56], "demand": 27, "service": 10, "windows": [{"day": 4, "start": 67, "end": 138}, {"day": 5, "start": 109, "end": 180}, {"day": 8, "start": 105, "end": 176}, {"day": 14, "start": 113, "end": 184}, {"day": 16, "start": 108, "end": 179}, {"day": 18, "start": 44, "end": 115}, {"day": 22, "start": 61, "end": 132}, {"day": 23, "start": 38, "end": 109}]}, "048": {"coords": [13, 52], "demand": 36, "service": 10, "windows": [{"day": 6, "start": 80, "end": 144}, {"day": 9, "start": 108, "end": 172}]}, "049": {"coords": [6, 68], "demand": 30, "service": 10, "windows": [{"day": 1, "start": 44, "end": 83}, {"day": 6, "start": 126, "end": 165}, {"day": 13, "start": 54, "end": 93}, {"day": 15, "start": 90, "end": 129}, {"day": 18, "start": 101, "end": 140}, {"day": 24, "start": 114, "end": 153}]}, "050": {"coords": [47, 47], "demand": 13, "service": 10, "windows": [{"day": 1, "start": 147, "end": 200}, {"day": 3, "start": 59, "end": 112}, {"day": 10, "start": 51, "end": 104}, {"day": 12, "start": 129, "end": 182}, {"day": 16, "start": 120, "end": 173}, {"day": 21, "start": 146, "end": 199}]}, "051": {"coords": [49, 58], "demand": 10, "service": 10, "windows": [{"day": 0, "start": 96, "end": 153}, {"day": 10, "start": 88, "end": 145}, {"day": 12, "start": 45, "end": 102}, {"day": 14, "start": 111, "end": 168}, {"day": 17, "start": 98, "end": 155}, {"day": 18, "start": 31, "end": 88}]}, "052": {"coords": [27, 43], "demand": 9, "service": 10, "windows": [{"day": 3, "start": 13, "end": 74}, {"day": 8, "start": 102, "end": 163}, {"day": 12, "start": 120, "end": 181}, {"day": 24, "start": 42, "end": 103}]}, "053": {"coords": [37, 31], "demand": 14, "service": 10, "windows": [{"day": 17, "start": 91, "end": 140}, {"day": 19, "start": 103, "end": 152}]}, "054": {"coords": [57, 29], "demand": 18, "service": 10, "windows": [{"day": 6, "start": 83, "end": 136}, {"day": 13, "start": 34, "end": 87}, {"day": 16, "start": 46, "end": 99}, {"day": 20, "start": 71, "end": 124}, {"day": 22, "start": 128, "end": 181}]}, "055": {"coords": [63, 23], "demand": 2, "service": 10, "windows": [{"day": 0, "start": 125, "end": 184}, {"day": 11, "start": 57, "end": 116}, {"day": 22, "start": 44, "end": 103}]}, "056": {"coords": [53, 12], "demand": 6, "service": 10, "windows": [{"day": 8, "start": 43, "end": 100}, {"day": 13, "start": 100, "end": 157}, {"day": 24, "start": 122, "end": 179}]}, "057": {"coords": [32, 12], "demand": 7, "service": 10, "windows": [{"day": 7, "start": 80, "end": 137}, {"day": 14, "start": 62, "end": 119}, {"day": 17, "start": 31, "end": 88}, {"day": 18, "start": 28, "end": 85}, {"day": 21, "start": 139, "end": 196}]}, "058": {"coords": [36, 26], "demand": 18, "service": 10, "windows": [{"day": 0, "start": 110, "end": 173}, {"day": 1, "start": 96, "end": 159}, {"day": 6, "start": 121, "end": 184}, {"day": 7, "start": 136, "end": 199}, {"day": 16, "start": 21, "end": 84}, {"day": 17, "start": 72, "end": 135}]}, "059": {"coords": [21, 24], "demand": 28, "service": 10, "windows": [{"day": 5, "start": 89, "end": 172}, {"day": 12, "start": 46, "end": 129}, {"day": 21, "start": 44, "end": 127}, {"day": 22, "start": 70, "end": 153}]}, "060": {"coords": [17, 34], "demand": 3, "service": 10, "windows": [{"day": 2, "start": 104, "end": 169}, {"day": 3, "start": 101, "end": 166}, {"day": 7, "start": 96, "end": 161}, {"day": 10, "start": 72, "end": 137}, {"day": 13, "start": 21, "end": 86}, {"day": 17, "start": 129, "end": 194}, {"day": 21, "start": 76, "end": 141}]}, "061": {"coords": [12, 24], "demand": 13, "service": 10, "windows": [{"day": 5, "start": 45, "end": 96}, {"day": 14, "start": 103, "end": 154}, {"day": 19, "start": 81, "end": 132}, {"day": 23, "start": 63, "end": 114}]}, "062": {"coords": [24, 58], "demand": 19, "service": 10, "windows": [{"day": 1, "start": 95, "end": 160}, {"day": 5, "start": 89, "end": 154}, {"day": 9, "start": 38, "end": 103}, {"day": 13, "start": 99, "end": 164}, {"day": 14, "start": 35, "end": 100}]}, "063": {"coords": [27, 69], "demand": 10, "service": 10, "windows": [{"day": 16, "start": 76, "end": 145}, {"day": 20, "start": 113, "end": 182}, {"day": 21, "start": 49, "end": 118}, {"day": 22, "start": 70, "end": 139}]}, "064": {"coords": [15, 77], "demand": 9, "service": 10, "windows": [{"day": 5, "start": 106, "end": 165}, {"day": 7, "start": 77, "end": 136}, {"day": 11, "start": 48, "end": 107}, {"day": 19, "start": 78, "end": 137}, {"day": 22, "start": 54, "end": 113}]}, "065": {"coords": [62, 77], "demand": 20, "service": 10, "windows": [{"day": 6, "start": 73, "end": 137}, {"day": 7, "start": 53, "end": 117}, {"day": 16, "start": 98, "end": 162}]}, "066": {"coords": [49, 73], "demand": 25, "service": 10, "windows": [{"day": 0, "start": 108, "end": 163}, {"day": 5, "start": 111, "end": 166}, {"day": 8, "start": 94, "end": 149}, {"day": 11, "start": 112, "end": 167}, {"day": 12, "start": 115, "end": 170}, {"day": 20, "start": 99, "end": 154}, {"day": 23, "start": 62, "end": 117}]}, "067": {"coords": [67, 5], "demand": 25, "service": 10, "windows": [{"day": 3, "start": 55, "end": 112}, {"day": 7, "start": 75, "end": 132}, {"day": 16, "start": 75, "end": 132}, {"day": 20, "start": 52, "end": 109}]}, "068": {"coords": [56, 39], "demand": 36, "service": 10, "windows": [{"day": 11, "start": 125, "end": 184}, {"day": 14, "start": 72, "end": 131}, {"day": 17, "start": 126, "end": 185}]}, "069": {"coords": [37, 47], "demand": 6, "service": 10, "windows": [{"day": 5, "start": 68, "end": 131}, {"day": 7, "start": 48, "end": 111}, {"day": 19, "start": 62, "end": 125}, {"day": 22, "start": 64, "end": 127}]}, "070": {"coords": [37, 56], "demand": 5, "service": 10, "windows": [{"day": 12, "start": 43, "end": 118}, {"day": 24, "start": 90, "end": 165}]}, "071": {"coords": [57, 68], "demand": 15, "service": 10, "windows": [{"day": 7, "start": 115, "end": 170}, {"day": 13, "start": 117, "end": 172}, {"day": 14, "start": 122, "end": 177}, {"day": 16, "start": 50, "end": 105}, {"day": 24, "start": 124, "end": 179}]}, "072": {"coords": [47, 16], "demand": 25, "service": 10, "windows": [{"day": 16, "start": 107, "end": 181}, {"day": 19, "start": 121, "end": 195}, {"day": 20, "start": 46, "end": 120}, {"day": 24, "start": 120, "end": 194}]}, "073": {"coords": [44, 17], "demand": 9, "service": 10, "windows": [{"day": 2, "start": 66, "end": 119}, {"day": 5, "start": 26, "end": 79}, {"day": 13, "start": 101, "end": 154}, {"day": 15, "start": 71, "end": 124}, {"day": 22, "start": 121, "end": 174}]}, "074": {"coords": [46, 13], "demand": 8, "service": 10, "windows": [{"day": 5, "start": 132, "end": 193}, {"day": 12, "start": 36, "end": 97}, {"day": 17, "start": 106, "end": 167}, {"day": 23, "start": 43, "end": 104}]}, "075": {"coords": [49, 11], "demand": 18, "service": 10, "windows": [{"day": 2, "start": 70, "end": 127}, {"day": 3, "start": 133, "end": 190}, {"day": 5, "start": 102, "end": 159}, {"day": 7, "start": 54, "end": 111}, {"day": 12, "start": 68, "end": 125}, {"day": 19, "start": 79, "end": 136}, {"day": 22, "start": 37, "end": 94}, {"day": 23, "start": 32, "end": 89}]}, "076": {"coords": [49, 42], "demand": 13, "service": 10, "windows": [{"day": 14, "start": 114, "end": 165}, {"day": 18, "start": 35, "end": 86}, {"day": 23, "start": 145, "end": 196}, {"day": 24, "start": 26, "end": 77}]}, "077": {"coords": [53, 43], "demand": 14, "service": 10, "windows": [{"day": 1, "start": 66, "end": 130}, {"day": 2, "start": 54, "end": 118}]}, "078": {"coords": [61, 52], "demand": 3, "service": 10, "windows": [{"day": 1, "start": 90, "end": 149}, {"day": 5, "start": 88, "end": 147}, {"day": 11, "start": 86, "end": 145}]}, "079": {"coords": [57, 48], "demand": 23, "service": 10, "windows": [{"day": 0, "start": 123, "end": 172}, {"day": 2, "start": 116, "end": 165}, {"day": 4, "start": 144, "end": 193}, {"day": 7, "start": 71, "end": 120}, {"day": 10, "start": 89, "end": 138}, {"day": 17, "start": 50, "end": 99}, {"day": 20, "start": 97, "end": 146}]}, "080": {"coords": [56, 37], "demand": 6, "service": 10, "windows": [{"day": 5, "start": 36, "end": 99}, {"day": 8, "start": 56, "end": 119}, {"day": 20, "start": 24, "end": 87}]}, "081": {"coords": [55, 54], "demand": 26, "service": 10, "windows": [{"day": 1, "start": 100, "end": 141}, {"day": 3, "start": 40, "end": 81}, {"day": 6, "start": 103, "end": 144}, {"day": 16, "start": 51, "end": 92}, {"day": 19, "start": 57, "end": 98}, {"day": 22, "start": 106, "end": 147}, {"day": 24, "start": 142, "end": 183}]}, "082": {"coords": [15, 47], "demand": 16, "service": 10, "windows": [{"day": 3, "start": 99, "end": 160}, {"day": 4, "start": 92, "end": 153}, {"day": 9, "start": 116, "end": 177}, {"day": 15, "start": 42, "end": 103}, {"day": 20, "start": 92, "end": 153}, {"day": 21, "start": 64, "end": 125}]}, "083": {"coords": [14, 37], "demand": 11, "service": 10, "windows": [{"day": 6, "start": 84, "end": 152}, {"day": 12, "start": 70, "end": 138}, {"day": 13, "start": 97, "end": 165}, {"day": 15, "start": 39, "end": 107}, {"day": 23, "start": 30, "end": 98}]}, "084": {"coords": [11, 31], "demand": 7, "service": 10, "windows": [{"day": 2, "start": 131, "end": 180}, {"day": 6, "start": 115, "end": 164}, {"day": 17, "start": 76, "end": 125}, {"day": 18, "start": 111, "end": 160}, {"day": 21, "start": 54, "end": 103}]}, "085": {"coords": [16, 22], "demand": 41, "service": 10, "windows": [{"day": 4, "start": 142, "end": 193}, {"day": 22, "start": 49, "end": 100}]}, "086": {"coords": [4, 18], "demand": 35, "service": 10, "windows": [{"day": 1, "start": 66, "end": 115}, {"day": 3, "start": 71, "end": 120}, {"day": 11, "start": 51, "end": 100}, {"day": 15, "start": 53, "end": 102}, {"day": 20, "start": 117, "end": 166}, {"day": 23, "start": 77, "end": 126}]}, "087": {"coords": [28, 18], "demand": 26, "service": 10, "windows": [{"day": 3, "start": 94, "end": 131}, {"day": 8, "start": 131, "end": 168}, {"day": 9, "start": 58, "end": 95}, {"day": 13, "start": 57, "end": 94}, {"day": 17, "start": 59, "end": 96}, {"day": 18, "start": 156, "end": 193}, {"day": 20, "start": 28, "end": 65}, {"day": 23, "start": 112, "end": 149}]}, "088": {"coords": [26, 52], "demand": 9, "service": 10, "windows": [{"day": 0, "start": 83, "end": 140}, {"day": 2, "start": 130, "end": 187}, {"day": 5, "start": 125, "end": 182}, {"day": 10, "start": 100, "end": 157}, {"day": 11, "start": 125, "end": 182}, {"day": 18, "start": 38, "end": 95}]}, "089": {"coords": [26, 35], "demand": 15, "service": 10, "windows": [{"day": 2, "start": 36, "end": 108}, {"day": 10, "start": 124, "end": 196}, {"day": 11, "start": 94, "end": 166}, {"day": 18, "start": 45, "end": 117}, {"day": 23, "start": 73, "end": 145}]}, "090": {"coords": [31, 67], "demand": 3, "service": 10, "windows": [{"day": 18, "start": 132, "end": 185}]}, "091": {"coords": [15, 19], "demand": 1, "service": 10, "windows": [{"day": 0, "start": 26, "end": 88}, {"day": 4, "start": 86, "end": 148}, {"day": 19, "start": 78, "end": 140}, {"day": 21, "start": 108, "end": 170}, {"day": 22, "start": 71, "end": 133}]}, "092": {"coords": [22, 22], "demand": 2, "service": 10, "windows": [{"day": 9, "start": 121, "end": 191}, {"day": 15, "start": 26, "end": 96}, {"day": 18, "start": 54, "end": 124}, {"day": 22, "start": 37, "end": 107}, {"day": 23, "start": 62, "end": 132}]}, "093": {"coords": [18, 24], "demand": 22, "service": 10, "windows": [{"day": 1, "start": 68, "end": 138}, {"day": 5, "start": 78, "end": 148}, {"day": 7, "start": 34, "end": 104}, {"day": 13, "start": 90, "end": 160}, {"day": 20, "start": 54, "end": 124}]}, "094": {"coords": [26, 27], "demand": 27, "service": 10, "windows": [{"day": 0, "start": 109, "end": 156}, {"day": 1, "start": 44, "end": 91}, {"day": 2, "start": 34, "end": 81}]}, "095": {"coords": [25, 24], "demand": 20, "service": 10, "windows": [{"day": 0, "start": 127, "end": 191}, {"day": 13, "start": 64, "end": 128}, {"day": 17, "start": 67, "end": 131}, {"day": 22, "start": 41, "end": 105}, {"day": 23, "start": 141, "end": 205}, {"day": 24, "start": 26, "end": 90}]}, "096": {"coords": [22, 27], "demand": 11, "service": 10, "windows": [{"day": 5, "start": 21, "end": 72}, {"day": 10, "start": 91, "end": 142}, {"day": 17, "start": 25, "end": 76}, {"day": 18, "start": 113, "end": 164}]}, "097": {"coords": [25, 21], "demand": 12, "service": 10, "windows": [{"day": 5, "start": 128, "end": 173}]}, "098": {"coords": [19, 21], "demand": 10, "service": 10, "windows": [{"day": 1, "start": 65, "end": 126}, {"day": 2, "start": 127, "end": 188}, {"day": 6, "start": 99, "end": 160}, {"day": 7, "start": 105, "end": 166}, {"day": 9, "start": 88, "end": 149}, {"day": 17, "start": 83, "end": 144}, {"day": 18, "start": 136, "end": 197}, {"day": 19, "start": 36, "end": 97}]}, "099": {"coords": [20, 26], "demand": 9, "service": 10, "windows": [{"day": 3, "start": 93, "end": 148}, {"day": 11, "start": 41, "end": 96}, {"day": 14, "start": 26, "end": 81}, {"day": 16, "start": 61, "end": 116}, {"day": 18, "start": 53, "end": 108}, {"day": 19, "start": 52, "end": 107}, {"day": 21, "start": 34, "end": 89}]}, "100": {"coords": [18, 18], "demand": 17, "service": 10, "windows": [{"day": 0, "start": 87, "end": 159}, {"day": 2, "start": 116, "end": 188}, {"day": 6, "start": 38, "end": 110}, {"day": 7, "start": 72, "end": 144}, {"day": 10, "start": 105, "end": 177}, {"day": 12, "start": 95, "end": 167}, {"day": 24, "start": 76, "end": 148}]}}}