{"num_c": 60, "num_v": 4, "vehicles": {"0": [100, 6], "1": [150, 6], "2": [200, 6], "3": [250, 6]}, "customers": {"00": {"coords": [-3.638, 16.114], "demand": 0, "service": 0, "windows": [{"day": 0, "start": 0, "end": 1000}, {"day": 1, "start": 0, "end": 1000}, {"day": 2, "start": 0, "end": 1000}, {"day": 3, "start": 0, "end": 1000}]}, "01": {"coords": [-22.522, 18.536], "demand": 8, "service": 4, "windows": [{"day": 3, "start": 345, "end": 436}, {"day": 2, "start": 345, "end": 436}, {"day": 1, "start": 345, "end": 436}, {"day": 0, "start": 345, "end": 436}]}, "02": {"coords": [-93.097, 84.552], "demand": 21, "service": 20, "windows": [{"day": 3, "start": 352, "end": 472}, {"day": 2, "start": 352, "end": 472}]}, "03": {"coords": [-15.387, 67.053], "demand": 13, "service": 17, "windows": [{"day": 3, "start": 133, "end": 289}, {"day": 2, "start": 133, "end": 289}]}, "04": {"coords": [-12.848, 51.459], "demand": 17, "service": 4, "windows": [{"day": 0, "start": 293, "end": 457}]}, "05": {"coords": [1.19, 56.055], "demand": 23, "service": 6, "windows": [{"day": 3, "start": 75, "end": 189}, {"day": 2, "start": 75, "end": 189}]}, "06": {"coords": [-12.598, 48.462], "demand": 23, "service": 11, "windows": [{"day": 2, "start": 83, "end": 204}, {"day": 1, "start": 83, "end": 204}]}, "07": {"coords": [3.345, 17.041], "demand": 20, "service": 9, "windows": [{"day": 2, "start": 467, "end": 562}, {"day": 1, "start": 467, "end": 562}]}, "08": {"coords": [-41.425, 78.906], "demand": 25, "service": 21, "windows": [{"day": 3, "start": 128, "end": 232}, {"day": 2, "start": 128, "end": 232}, {"day": 1, "start": 128, "end": 232}, {"day": 0, "start": 128, "end": 232}]}, "09": {"coords": [13.965, 91.473], "demand": 23, "service": 19, "windows": [{"day": 2, "start": 323, "end": 450}, {"day": 1, "start": 323, "end": 450}]}, "10": {"coords": [-73.962, 74.353], "demand": 16, "service": 1, "windows": [{"day": 1, "start": 423, "end": 519}]}, "11": {"coords": [-81.995, -2.673], "demand": 16, "service": 21, "windows": [{"day": 2, "start": 207, "end": 343}, {"day": 1, "start": 207, "end": 343}]}, "12": {"coords": [-51.465, 30.646], "demand": 21, "service": 21, "windows": [{"day": 3, "start": 100, "end": 253}, {"day": 2, "start": 100, "end": 253}, {"day": 1, "start": 100, "end": 253}, {"day": 0, "start": 100, "end": 253}]}, "13": {"coords": [2.789, 54.303], "demand": 8, "service": 23, "windows": [{"day": 3, "start": 198, "end": 365}, {"day": 2, "start": 198, "end": 365}, {"day": 1, "start": 198, "end": 365}, {"day": 0, "start": 198, "end": 365}]}, "14": {"coords": [70.404, -72.443], "demand": 15, "service": 14, "windows": [{"day": 2, "start": 337, "end": 465}, {"day": 1, "start": 337, "end": 465}]}, "15": {"coords": [36.731, -50.226], "demand": 5, "service": 24, "windows": [{"day": 3, "start": 156, "end": 287}, {"day": 2, "start": 156, "end": 287}, {"day": 1, "start": 156, "end": 287}, {"day": 0, "start": 156, "end": 287}]}, "16": {"coords": [-34.302, 25.995], "demand": 4, "service": 25, "windows": [{"day": 3, "start": 332, "end": 446}, {"day": 2, "start": 332, "end": 446}, {"day": 1, "start": 332, "end": 446}, {"day": 0, "start": 332, "end": 446}]}, "17": {"coords": [5.243, -67.346], "demand": 8, "service": 21, "windows": [{"day": 3, "start": 183, "end": 362}, {"day": 2, "start": 183, "end": 362}, {"day": 1, "start": 183, "end": 362}, {"day": 0, "start": 183, "end": 362}]}, "18": {"coords": [28.4, -35.272], "demand": 13, "service": 24, "windows": [{"day": 1, "start": 181, "end": 319}, {"day": 0, "start": 181, "end": 319}]}, "19": {"coords": [-99.67, 11.475], "demand": 14, "service": 10, "windows": [{"day": 3, "start": 143, "end": 251}, {"day": 0, "start": 143, "end": 251}]}, "20": {"coords": [-56.812, 45.544], "demand": 18, "service": 3, "windows": [{"day": 3, "start": 312, "end": 445}]}, "21": {"coords": [-43.549, 30.188], "demand": 12, "service": 11, "windows": [{"day": 3, "start": 375, "end": 548}, {"day": 0, "start": 375, "end": 548}]}, "22": {"coords": [-23.102, 61.108], "demand": 8, "service": 15, "windows": [{"day": 1, "start": 302, "end": 472}, {"day": 0, "start": 302, "end": 472}]}, "23": {"coords": [-8.099, 40.924], "demand": 6, "service": 15, "windows": [{"day": 2, "start": 460, "end": 622}, {"day": 1, "start": 460, "end": 622}]}, "24": {"coords": [75.848, 86.322], "demand": 14, "service": 5, "windows": [{"day": 2, "start": 307, "end": 406}, {"day": 1, "start": 307, "end": 406}]}, "25": {"coords": [28.937, -22.119], "demand": 12, "service": 4, "windows": [{"day": 3, "start": 185, "end": 345}, {"day": 0, "start": 185, "end": 345}]}, "26": {"coords": [-89.935, 64.575], "demand": 10, "service": 25, "windows": [{"day": 1, "start": 328, "end": 484}, {"day": 0, "start": 328, "end": 484}]}, "27": {"coords": [30.255, -25.458], "demand": 20, "service": 23, "windows": [{"day": 1, "start": 237, "end": 340}, {"day": 0, "start": 237, "end": 340}]}, "28": {"coords": [-85.394, 44.781], "demand": 18, "service": 18, "windows": [{"day": 3, "start": 213, "end": 387}, {"day": 2, "start": 213, "end": 387}]}, "29": {"coords": [-44.159, 41.98], "demand": 4, "service": 12, "windows": [{"day": 3, "start": 291, "end": 432}, {"day": 2, "start": 291, "end": 432}]}, "30": {"coords": [-49.097, 5.194], "demand": 17, "service": 17, "windows": [{"day": 3, "start": 385, "end": 489}]}, "31": {"coords": [-27.356, 38.708], "demand": 6, "service": 19, "windows": [{"day": 3, "start": 282, "end": 372}, {"day": 2, "start": 282, "end": 372}, {"day": 1, "start": 282, "end": 372}, {"day": 0, "start": 282, "end": 372}]}, "32": {"coords": [34.998, 16.058], "demand": 9, "service": 17, "windows": [{"day": 3, "start": 256, "end": 406}, {"day": 0, "start": 256, "end": 406}]}, "33": {"coords": [13.953, -25.842], "demand": 7, "service": 16, "windows": [{"day": 3, "start": 389, "end": 564}]}, "34": {"coords": [1.617, -72.998], "demand": 1, "service": 12, "windows": [{"day": 1, "start": 261, "end": 396}]}, "35": {"coords": [11.786, 15.375], "demand": 22, "service": 18, "windows": [{"day": 1, "start": 438, "end": 600}, {"day": 0, "start": 438, "end": 600}]}, "36": {"coords": [-34.686, 24.048], "demand": 24, "service": 1, "windows": [{"day": 3, "start": 215, "end": 393}, {"day": 2, "start": 215, "end": 393}, {"day": 1, "start": 215, "end": 393}, {"day": 0, "start": 215, "end": 393}]}, "37": {"coords": [-44.556, 19.623], "demand": 16, "service": 7, "windows": [{"day": 1, "start": 235, "end": 413}]}, "38": {"coords": [-13.123, 2.655], "demand": 19, "service": 8, "windows": [{"day": 3, "start": 350, "end": 522}, {"day": 2, "start": 350, "end": 522}, {"day": 1, "start": 350, "end": 522}, {"day": 0, "start": 350, "end": 522}]}, "39": {"coords": [-1.367, -9.375], "demand": 4, "service": 23, "windows": [{"day": 1, "start": 100, "end": 190}, {"day": 0, "start": 100, "end": 190}]}, "40": {"coords": [-7.013, 53.424], "demand": 22, "service": 17, "windows": [{"day": 3, "start": 106, "end": 218}, {"day": 2, "start": 106, "end": 218}]}, "41": {"coords": [16.37, -15.546], "demand": 23, "service": 7, "windows": [{"day": 1, "start": 324, "end": 494}]}, "42": {"coords": [-46.46, 48.151], "demand": 8, "service": 10, "windows": [{"day": 3, "start": 140, "end": 299}, {"day": 2, "start": 140, "end": 299}]}, "43": {"coords": [-17.572, -79.858], "demand": 19, "service": 19, "windows": [{"day": 2, "start": 270, "end": 386}, {"day": 1, "start": 270, "end": 386}]}, "44": {"coords": [26.794, 57.44], "demand": 4, "service": 15, "windows": [{"day": 3, "start": 368, "end": 461}, {"day": 0, "start": 368, "end": 461}]}, "45": {"coords": [51.898, 89.935], "demand": 18, "service": 5, "windows": [{"day": 3, "start": 404, "end": 534}, {"day": 2, "start": 404, "end": 534}, {"day": 1, "start": 404, "end": 534}, {"day": 0, "start": 404, "end": 534}]}, "46": {"coords": [-1.782, -45.105], "demand": 6, "service": 24, "windows": [{"day": 1, "start": 381, "end": 548}]}, "47": {"coords": [8.783, -69.36], "demand": 19, "service": 22, "windows": [{"day": 1, "start": 235, "end": 364}, {"day": 0, "start": 235, "end": 364}]}, "48": {"coords": [-65.692, 41.821], "demand": 2, "service": 2, "windows": [{"day": 1, "start": 213, "end": 387}]}, "49": {"coords": [27.814, -24.841], "demand": 18, "service": 15, "windows": [{"day": 1, "start": 269, "end": 424}]}, "50": {"coords": [-33.502, 7.501], "demand": 17, "service": 4, "windows": [{"day": 3, "start": 178, "end": 355}, {"day": 2, "start": 178, "end": 355}, {"day": 1, "start": 178, "end": 355}, {"day": 0, "start": 178, "end": 355}]}, "51": {"coords": [-11.42, -25.311], "demand": 13, "service": 5, "windows": [{"day": 1, "start": 71, "end": 218}, {"day": 0, "start": 71, "end": 218}]}, "52": {"coords": [16.614, -30.084], "demand": 11, "service": 5, "windows": [{"day": 1, "start": 109, "end": 209}]}, "53": {"coords": [17.883, -68.549], "demand": 22, "service": 6, "windows": [{"day": 1, "start": 137, "end": 250}, {"day": 0, "start": 137, "end": 250}]}, "54": {"coords": [5.292, -51.556], "demand": 14, "service": 2, "windows": [{"day": 3, "start": 444, "end": 596}]}, "55": {"coords": [5.615, -87.604], "demand": 13, "service": 5, "windows": [{"day": 2, "start": 314, "end": 453}, {"day": 1, "start": 314, "end": 453}]}, "56": {"coords": [-81.604, 30.64], "demand": 3, "service": 25, "windows": [{"day": 1, "start": 279, "end": 422}, {"day": 0, "start": 279, "end": 422}]}, "57": {"coords": [-97.9, 67.92], "demand": 21, "service": 10, "windows": [{"day": 1, "start": 128, "end": 253}]}, "58": {"coords": [10.931, -29.095], "demand": 20, "service": 18, "windows": [{"day": 3, "start": 99, "end": 276}, {"day": 2, "start": 99, "end": 276}]}, "59": {"coords": [47.546, -20.782], "demand": 9, "service": 5, "windows": [{"day": 3, "start": 318, "end": 485}, {"day": 2, "start": 318, "end": 485}, {"day": 1, "start": 318, "end": 485}, {"day": 0, "start": 318, "end": 485}]}, "60": {"coords": [-39.551, -10.968], "demand": 17, "service": 3, "windows": [{"day": 1, "start": 338, "end": 468}, {"day": 0, "start": 338, "end": 468}]}}}